{"mc":{
	"body957_1_eff":{
		"frameRate":7,
		"labels":[
			{"name":"body957_1_eff","frame":1,"end":6}
			
			],
		"events":[
			
			],
		"frames":[
			
			{
			"res":"00000",
			"x":-140,
			"y":-139
			},
			{
			"res":"00001",
			"x":-150,
			"y":-136
			},
			{
			"res":"00002",
			"x":-148,
			"y":-141
			},
			{
			"res":"00003",
			"x":-143,
			"y":-139
			},
			{
			"res":"00004",
			"x":-149,
			"y":-153
			},
			{
			"res":"00005",
			"x":-150,
			"y":-140
			}
			]
}},
	"res":{
		"00005":{"x":318,"y":508,"w":313,"h":484},
		"00004":{"x":1,"y":1,"w":312,"h":501},
		"00002":{"x":1,"y":508,"w":311,"h":488},
		"00000":{"x":637,"y":487,"w":303,"h":479},
		"00001":{"x":627,"y":1,"w":303,"h":480},
		"00003":{"x":319,"y":1,"w":302,"h":487}
	}}