{"mc":{"weapon924_0_0c":{"frameRate":15,"frames":[{"res":"128","x":-10,"y":-170},{"res":"129","x":-50,"y":-203},{"res":"130","x":-81,"y":-189},{"res":"131","x":-61,"y":-167},{"res":"132","x":-34,"y":-201},{"res":"133","x":-30,"y":-172},{"res":"601","x":12,"y":-143}]}},"res":{"128":{"x":0,"y":0,"w":80,"h":139},"129":{"x":80,"y":0,"w":88,"h":144},"130":{"x":168,"y":0,"w":126,"h":123},"131":{"x":294,"y":0,"w":107,"h":95},"132":{"x":401,"y":0,"w":89,"h":116},"133":{"x":490,"y":0,"w":90,"h":113},"601":{"x":580,"y":0,"w":86,"h":97}}}